{
    "skeleton": {
        "hash": "1vCXn5Y2ZEw",
        "spine": "4.2.20",
        "x": -51.34,
        "y": -69.5,
        "width": 98.84,
        "height": 121.89,
        "images": "C:\\Users\\cyivs\\OneDrive\\Desktop\\Spine_Project\\HTML\\static\\Image\\Saved",
        "audio": "E:/SpineSymbol/spine_material2/48(308)"
    },
    "bones": [
        {
            "name": "root",
            "scaleX": 0.5,
            "scaleY": 0.5
        },
        {
            "name": "_subroot",
            "parent": "root"
        },
        {
            "name": "h_soda",
            "parent": "_subroot"
        },
        {
            "name": "h_soda_ctrl",
            "parent": "h_soda",
            "y": -60,
            "color": "22ff34ff"
        },
        {
            "name": "h_soda_ctrl_opp",
            "parent": "h_soda",
            "y": 60
        }
    ],
    "slots": [
        {
            "name": "h_soda_base",
            "bone": "h_soda",
            "attachment": "Je_enlarge.png"
        }
    ],
    "transform": [
        {
            "name": "h_soda_ctrl",
            "bones": [
                "h_soda_ctrl_opp"
            ],
            "target": "h_soda_ctrl",
            "y": 120,
            "mixRotate": 0,
            "mixX": -1,
            "mixScaleX": 0,
            "mixShearY": 0
        }
    ],
    "skins": [
        {
            "name": "default",
            "attachments": {
                "h_soda_base": {
                    "Je_enlarge.png": {
                        "type": "mesh",
                        "uvs": [
                            0.92151,
                            0.8332,
                            0.83955,
                            0.92967,
                            0.67799,
                            0.99999,
                            0.48105,
                            0.98467,
                            0.35156,
                            0.92877,
                            0.27528,
                            0.77475,
                            0.17992,
                            0.59236,
                            0.10945,
                            0.45754,
                            0.01437,
                            0.39459,
                            0.00663,
                            0.24598,
                            0.07296,
                            0.13525,
                            0.23342,
                            0.06311,
                            0.43035,
                            0.02254,
                            0.66266,
                            0.0009,
                            0.86402,
                            0.03246,
                            0.95799,
                            0.10352,
                            1,
                            0.25033,
                            0.94362,
                            0.32951,
                            0.93697,
                            0.4731,
                            0.92814,
                            0.66385,
                            0.79643,
                            0.75311,
                            0.6194,
                            0.7973,
                            0.43352,
                            0.79729,
                            0.78206,
                            0.58197,
                            0.56191,
                            0.62885,
                            0.35502,
                            0.61713,
                            0.73231,
                            0.30352,
                            0.49447,
                            0.36303,
                            0.26769,
                            0.37205,
                            0.87382,
                            0.23697,
                            0.47126,
                            0.17746,
                            0.09523,
                            0.33074,
                            0.30961,
                            0.48819,
                            0.52629,
                            0.48026,
                            0.75182,
                            0.42471
                        ],
                        "triangles": [
                            30,
                            12,
                            13,
                            11,
                            12,
                            30,
                            29,
                            14,
                            15,
                            29,
                            15,
                            16,
                            29,
                            26,
                            13,
                            29,
                            13,
                            14,
                            30,
                            13,
                            26,
                            17,
                            29,
                            16,
                            28,
                            31,
                            10,
                            11,
                            28,
                            10,
                            9,
                            10,
                            31,
                            27,
                            30,
                            26,
                            30,
                            28,
                            11,
                            27,
                            28,
                            30,
                            8,
                            9,
                            31,
                            17,
                            26,
                            29,
                            27,
                            26,
                            34,
                            8,
                            31,
                            7,
                            25,
                            32,
                            33,
                            6,
                            32,
                            25,
                            24,
                            33,
                            23,
                            25,
                            33,
                            24,
                            19,
                            23,
                            18,
                            20,
                            23,
                            19,
                            24,
                            23,
                            20,
                            5,
                            6,
                            25,
                            22,
                            25,
                            24,
                            21,
                            22,
                            24,
                            5,
                            25,
                            22,
                            20,
                            21,
                            24,
                            0,
                            20,
                            19,
                            4,
                            5,
                            22,
                            1,
                            20,
                            0,
                            21,
                            20,
                            1,
                            3,
                            22,
                            21,
                            2,
                            3,
                            21,
                            4,
                            22,
                            3,
                            1,
                            2,
                            21,
                            17,
                            34,
                            26,
                            18,
                            34,
                            17,
                            33,
                            27,
                            34,
                            32,
                            28,
                            27,
                            32,
                            27,
                            33,
                            7,
                            28,
                            32,
                            23,
                            34,
                            18,
                            6,
                            7,
                            32,
                            33,
                            34,
                            23,
                            7,
                            31,
                            28
                        ],
                        "vertices": [
                            1,
                            2,
                            155.25661016949152,
                            -187.0462711864407,
                            1,
                            2,
                            2,
                            122.63661016949152,
                            -234.1262711864407,
                            0.92,
                            3,
                            122.63661016949152,
                            -174.1262711864407,
                            0.08,
                            2,
                            2,
                            58.33661016949153,
                            -268.44627118644064,
                            0.9,
                            3,
                            58.33661016949153,
                            -208.44627118644064,
                            0.1,
                            2,
                            2,
                            -20.043389830508474,
                            -260.9662711864407,
                            0.92,
                            3,
                            -20.043389830508474,
                            -200.96627118644068,
                            0.08,
                            1,
                            2,
                            -71.58338983050848,
                            -233.6862711864407,
                            1,
                            1,
                            2,
                            -101.94338983050847,
                            -158.5262711864407,
                            1,
                            1,
                            2,
                            -139.9033898305085,
                            -69.50627118644069,
                            1,
                            2,
                            2,
                            -167.94338983050847,
                            -3.7262711864406786,
                            0.92,
                            3,
                            -167.94338983050847,
                            56.273728813559316,
                            0.08,
                            1,
                            2,
                            -205.7833898305085,
                            26.993728813559326,
                            1,
                            1,
                            2,
                            -208.86338983050848,
                            99.51372881355933,
                            1,
                            2,
                            2,
                            -182.4633898305085,
                            153.5537288135593,
                            0.92,
                            4,
                            -182.4633898305085,
                            93.5537288135593,
                            0.08,
                            2,
                            2,
                            -118.60338983050846,
                            188.7537288135593,
                            0.85,
                            4,
                            -118.60338983050846,
                            128.7537288135593,
                            0.15,
                            2,
                            2,
                            -40.223389830508474,
                            208.5537288135593,
                            0.82,
                            4,
                            -40.223389830508474,
                            148.5537288135593,
                            0.18,
                            2,
                            2,
                            52.23661016949153,
                            219.1137288135593,
                            0.85,
                            4,
                            52.23661016949153,
                            159.1137288135593,
                            0.15,
                            2,
                            2,
                            132.37661016949153,
                            203.7137288135593,
                            0.92,
                            4,
                            132.37661016949153,
                            143.7137288135593,
                            0.08,
                            1,
                            2,
                            169.7766101694915,
                            169.0337288135593,
                            1,
                            1,
                            2,
                            186.49661016949153,
                            97.39372881355932,
                            1,
                            2,
                            2,
                            164.05661016949153,
                            58.753728813559334,
                            0.92,
                            3,
                            164.05661016949153,
                            118.7537288135593,
                            0.08,
                            1,
                            2,
                            161.4166101694915,
                            -11.326271186440678,
                            1,
                            1,
                            2,
                            157.8966101694915,
                            -104.40627118644066,
                            1,
                            2,
                            2,
                            105.47661016949152,
                            -147.9662711864407,
                            0.85,
                            3,
                            105.47661016949152,
                            -87.96627118644071,
                            0.15,
                            2,
                            2,
                            35.01661016949153,
                            -169.5262711864407,
                            0.82,
                            3,
                            35.01661016949153,
                            -109.52627118644068,
                            0.18,
                            2,
                            2,
                            -38.963389830508476,
                            -169.5262711864407,
                            0.85,
                            3,
                            -38.963389830508476,
                            -109.52627118644068,
                            0.15,
                            2,
                            2,
                            99.75661016949152,
                            -64.44627118644068,
                            0.85,
                            3,
                            99.75661016949152,
                            -4.446271186440683,
                            0.15,
                            2,
                            2,
                            12.136610169491526,
                            -87.32627118644068,
                            0.82,
                            3,
                            12.136610169491526,
                            -27.326271186440678,
                            0.18,
                            2,
                            2,
                            -70.20338983050848,
                            -81.60627118644068,
                            0.85,
                            3,
                            -70.20338983050848,
                            -21.60627118644068,
                            0.15,
                            2,
                            2,
                            79.95661016949151,
                            71.43372881355933,
                            0.85,
                            3,
                            79.95661016949151,
                            131.4337288135593,
                            0.15,
                            2,
                            2,
                            -14.703389830508474,
                            42.39372881355932,
                            0.82,
                            3,
                            -14.703389830508474,
                            102.39372881355932,
                            0.18,
                            2,
                            2,
                            -104.96338983050848,
                            37.99372881355933,
                            0.85,
                            3,
                            -104.96338983050848,
                            97.99372881355931,
                            0.15,
                            2,
                            2,
                            136.2766101694915,
                            103.91372881355933,
                            0.92,
                            3,
                            136.2766101694915,
                            163.91372881355932,
                            0.08,
                            1,
                            2,
                            -23.943389830508476,
                            132.9537288135593,
                            1,
                            2,
                            2,
                            -173.6033898305085,
                            58.153728813559326,
                            0.92,
                            3,
                            -173.6033898305085,
                            118.15372881355931,
                            0.08,
                            2,
                            2,
                            -88.28338983050847,
                            -18.686271186440678,
                            0.85,
                            3,
                            -88.28338983050847,
                            41.31372881355932,
                            0.15,
                            2,
                            2,
                            -2.043389830508475,
                            -14.806271186440679,
                            0.82,
                            3,
                            -2.043389830508475,
                            45.19372881355932,
                            0.18,
                            2,
                            2,
                            87.71661016949153,
                            12.293728813559323,
                            0.85,
                            3,
                            87.71661016949153,
                            72.29372881355931,
                            0.15
                        ],
                        "hull": 20,
                        "edges": [
                            0,
                            2,
                            2,
                            4,
                            4,
                            6,
                            6,
                            8,
                            8,
                            10,
                            14,
                            16,
                            16,
                            18,
                            18,
                            20,
                            20,
                            22,
                            22,
                            24,
                            24,
                            26,
                            26,
                            28,
                            28,
                            30,
                            30,
                            32,
                            32,
                            34,
                            38,
                            0,
                            10,
                            12,
                            12,
                            14,
                            34,
                            36,
                            36,
                            38
                        ],
                        "width": 100,
                        "height": 122
                    }
                }
            }
        }
    ],
    "animations": {
        "win": {
            "bones": {
                "_subroot": {
                    "scale": [
                        {
                            "curve": [
                                0.025,
                                0.995,
                                0.05,
                                0.99,
                                0.025,
                                0.995,
                                0.05,
                                0.99
                            ]
                        },
                        {
                            "time": 0.0667,
                            "x": 0.99,
                            "y": 0.99,
                            "curve": [
                                0.1,
                                0.99,
                                0.167,
                                1.01,
                                0.1,
                                0.99,
                                0.167,
                                1.01
                            ]
                        },
                        {
                            "time": 0.2,
                            "x": 1.01,
                            "y": 1.01,
                            "curve": [
                                0.25,
                                1.01,
                                0.255,
                                1,
                                0.25,
                                1.01,
                                0.255,
                                1
                            ]
                        },
                        {
                            "time": 0.4
                        }
                    ]
                },
                "h_soda": {
                    "rotate": [
                        {
                            "curve": [
                                0.025,
                                0,
                                0.075,
                                5.96
                            ]
                        },
                        {
                            "time": 0.1,
                            "value": 5.96,
                            "curve": [
                                0.133,
                                5.96,
                                0.2,
                                -6.55
                            ]
                        },
                        {
                            "time": 0.2333,
                            "value": -6.55,
                            "curve": [
                                0.267,
                                -6.55,
                                0.333,
                                5.96
                            ]
                        },
                        {
                            "time": 0.3667,
                            "value": 5.96,
                            "curve": [
                                0.4,
                                5.96,
                                0.467,
                                0
                            ]
                        },
                        {
                            "time": 0.5
                        }
                    ]
                },
                "h_soda_ctrl": {
                    "translate": [
                        {
                            "curve": [
                                0.017,
                                0,
                                0.05,
                                9.92,
                                0.017,
                                0,
                                0.05,
                                -33.41
                            ]
                        },
                        {
                            "time": 0.0667,
                            "x": 9.92,
                            "y": -33.41,
                            "curve": [
                                0.117,
                                9.92,
                                0.217,
                                -14.38,
                                0.117,
                                -33.41,
                                0.217,
                                56.58
                            ]
                        },
                        {
                            "time": 0.2667,
                            "x": -14.38,
                            "y": 56.58,
                            "curve": [
                                0.325,
                                -14.38,
                                0.442,
                                0,
                                0.325,
                                56.58,
                                0.442,
                                0
                            ]
                        },
                        {
                            "time": 0.5
                        }
                    ]
                }
            }
        }
    }
}